dynast
