Metadata-Version: 2.1
Name: dynast-release
Version: 1.0.1
Summary: Complete splicing and labeling quantification from metabolic labeling scRNA-seq
Home-page: https://github.com/aristoteleo/dynast-release
Author: Kyung Hoi (Joseph) Min
Author-email: phoenixter96@gmail.com
License: MIT
Platform: UNKNOWN
Classifier: Development Status :: 4 - Beta
Classifier: Environment :: Console
Classifier: Intended Audience :: Science/Research
Classifier: License :: OSI Approved :: MIT License
Classifier: Operating System :: POSIX :: Linux
Classifier: Operating System :: MacOS
Classifier: Programming Language :: Python :: 3.7
Classifier: Programming Language :: Python :: 3.8
Classifier: Programming Language :: Python :: 3.9
Classifier: Topic :: Scientific/Engineering :: Bio-Informatics
Classifier: Topic :: Utilities
Requires-Python: >=3.7
